tango_simlib/__init__.py
tango_simlib/compat.py
tango_simlib/main.py
tango_simlib/model.py
tango_simlib/quantities.py
tango_simlib/sim_test_interface.py
tango_simlib/tango_launcher.py
tango_simlib/tango_sim_generator.py
tango_simlib/examples/__init__.py
tango_simlib/examples/mkat_vds.py
tango_simlib/examples/override_class.py
tango_simlib/examples/weather1.py
tango_simlib/examples/weather2.py
tango_simlib/examples/weather3.py
tango_simlib/tango_yaml_tools/__init__.py
tango_simlib/tango_yaml_tools/base.py
tango_simlib/tango_yaml_tools/main.py
tango_simlib/tests/__init__.py
tango_simlib/tests/test_dish.py
tango_simlib/tests/test_fandango_json_parser.py
tango_simlib/tests/test_quantities.py
tango_simlib/tests/test_sim_sdd_xml_parser.py
tango_simlib/tests/test_sim_test_interface.py
tango_simlib/tests/test_sim_xmi_parser.py
tango_simlib/tests/test_simdd_json_parser.py
tango_simlib/tests/test_tango_sim_generator.py
tango_simlib/tests/test_validator.py
tango_simlib/tests/test_yaml_builder.py
tango_simlib/tests/config_files/DishElementMaster.xmi
tango_simlib/tests/config_files/DishElementMaster_SimDD.json
tango_simlib/tests/config_files/MkatVds.xmi
tango_simlib/tests/config_files/MkatVds_SimDD.json
tango_simlib/tests/config_files/Weather.xmi
tango_simlib/tests/config_files/WeatherSimulator_CN.xml
tango_simlib/tests/config_files/Weather_SimDD.json
tango_simlib/tests/config_files/Weather_SimDD_2.json
tango_simlib/tests/config_files/Weather_SimDD_3.json
tango_simlib/tests/config_files/__init__.py
tango_simlib/tests/config_files/database2.fgo
tango_simlib/tests/config_files/devenum_test_case.xmi
tango_simlib/tests/config_files/multidevice.xmi
tango_simlib/utilities/SimDD.schema
tango_simlib/utilities/__init__.py
tango_simlib/utilities/base_parser.py
tango_simlib/utilities/fandango_json_parser.py
tango_simlib/utilities/helper_module.py
tango_simlib/utilities/sim_sdd_xml_parser.py
tango_simlib/utilities/sim_xmi_parser.py
tango_simlib/utilities/simdd_json_parser.py
tango_simlib-0.9.4.dist-info/LICENSE.txt
tango_simlib-0.9.4.dist-info/METADATA
tango_simlib-0.9.4.dist-info/WHEEL
tango_simlib-0.9.4.dist-info/entry_points.txt
tango_simlib-0.9.4.dist-info/top_level.txt
tango_simlib-0.9.4.dist-info/RECORD
