Metadata-Version: 2.1
Name: tango-simlib
Version: 0.9.4
Summary: Generic library for creating simulated TANGO devices.
Home-page: https://github.com/ska-sa/tango-simlib
Author: MeerKAT CAM Team
Author-email: cam@ska.ac.za
License: BSD
Download-URL: https://pypi.python.org/pypi/tango-simlib
Platform: OS Independent
Classifier: Intended Audience :: Developers
Classifier: License :: OSI Approved :: BSD License
Classifier: Operating System :: OS Independent
Classifier: Programming Language :: Python
Classifier: Programming Language :: Python :: 2
Classifier: Programming Language :: Python :: 2.7
Classifier: Programming Language :: Python :: 3
Classifier: Programming Language :: Python :: 3.5
Classifier: Programming Language :: Python :: 3.6
Classifier: Programming Language :: Python :: 3.7
Classifier: Programming Language :: Python :: 3.8
Classifier: Topic :: Software Development :: Libraries :: Python Modules
Requires-Python: >=2.7, !=3.0.*, !=3.1.*, !=3.2.*, !=3.3.*, !=3.4.*
Requires-Dist: future
Requires-Dist: numpy
Requires-Dist: PyTango (>=9.2.2)
Requires-Dist: pathlib
Requires-Dist: pyyaml
Requires-Dist: futures ; python_version < "3"
Requires-Dist: pyrsistent (==0.16.0) ; python_version < "3"
Requires-Dist: jsonschema (==3.2.0) ; python_version < "3"
Requires-Dist: pyrsistent ; python_version >= "3"
Requires-Dist: jsonschema ; python_version >= "3"
Provides-Extra: docs
Requires-Dist: sphinx-pypi-upload ; extra == 'docs'
Requires-Dist: numpydoc ; extra == 'docs'
Requires-Dist: Sphinx ; extra == 'docs'
Requires-Dist: mock ; extra == 'docs'
